Metadata-Version: 2.1
Name: vkcoinapi
Version: 1.2.5
Summary: UNKNOWN
Home-page: https://github.com/bixnel/vkcoinapi
Author: Bixnel
License: MIT
Platform: UNKNOWN
Classifier: Programming Language :: Python :: 3.6
